textual_calculator/__about__.py
textual_calculator/__init__.py
textual_calculator/calculator.py
textual_calculator/calculator.tcss
textual_calculator/entry_points.py
textual_calculator-0.0.2.dist-info/METADATA
textual_calculator-0.0.2.dist-info/WHEEL
textual_calculator-0.0.2.dist-info/entry_points.txt
textual_calculator-0.0.2.dist-info/licenses/LICENSE.txt
textual_calculator-0.0.2.dist-info/RECORD
