Metadata-Version: 2.1
Name: textual-calculator
Version: 0.0.2
Project-URL: Documentation, https://github.com/unknown/textual-calculator#readme
Project-URL: Issues, https://github.com/unknown/textual-calculator/issues
Project-URL: Source, https://github.com/unknown/textual-calculator
Author-email: Will McGugan <willmcgugan@gmail.com>
License-Expression: MIT
License-File: LICENSE.txt
Classifier: Development Status :: 4 - Beta
Classifier: Programming Language :: Python
Classifier: Programming Language :: Python :: 3.8
Classifier: Programming Language :: Python :: 3.9
Classifier: Programming Language :: Python :: 3.10
Classifier: Programming Language :: Python :: 3.11
Classifier: Programming Language :: Python :: 3.12
Classifier: Programming Language :: Python :: Implementation :: CPython
Classifier: Programming Language :: Python :: Implementation :: PyPy
Requires-Python: >=3.8
Requires-Dist: textual==0.47.1
